pylint/reporters/codeclimate_reporter.py
pylint_codeclimate/codeclimate_reporter.py
pylint_codeclimate-1.2.5.dist-info/LICENSE
pylint_codeclimate-1.2.5.dist-info/METADATA
pylint_codeclimate-1.2.5.dist-info/WHEEL
pylint_codeclimate-1.2.5.dist-info/top_level.txt
pylint_codeclimate-1.2.5.dist-info/zip-safe
pylint_codeclimate-1.2.5.dist-info/RECORD
