Metadata-Version: 2.1
Name: pylint-codeclimate
Version: 1.2.5
Summary: (deprecated, unmaintained)
Author-email: Julien Lecomte <julien@lecomte.at>
License: MIT
Project-URL: Homepage, https://gitlab.com/jlecomte/projects/python/pylint-codeclimate
Project-URL: Documentation, https://gitlab.com/jlecomte/projects/python/pylint-codeclimate/-/blob/master/readme.md
Project-URL: Source code, https://gitlab.com/jlecomte/projects/python/pylint-codeclimate
Project-URL: Bug tracker, https://gitlab.com/jlecomte/projects/python/pylint-codeclimate/-/issues
Classifier: License :: OSI Approved :: MIT License
Classifier: Intended Audience :: Developers
Classifier: Topic :: Software Development :: Quality Assurance
Classifier: Development Status :: 5 - Production/Stable
Classifier: Programming Language :: Python :: 3 :: Only
Classifier: Programming Language :: Python :: 3.6
Classifier: Programming Language :: Python :: 3.7
Classifier: Programming Language :: Python :: 3.8
Classifier: Programming Language :: Python :: 3.9
Requires-Python: >=3.6
License-File: LICENSE
Requires-Dist: pylint
